{"type":"Topology","objects":{"river_2550":{"type":"GeometryCollection","geometries":[{"type":"MultiLineString","arcs":[[0]],"properties":{"id":null,"RIVERNAME":"冬山河","BASIN_NO":"2550","BASIN_NAME":"冬山河","AREA":93.39652080393776}},{"type":"MultiLineString","arcs":[[1]],"properties":{"id":null,"RIVERNAME":"冬山河","BASIN_NO":"2550","BASIN_NAME":"冬山河","AREA":93.39652080393776}},{"type":"MultiLineString","arcs":[[2]],"properties":{"id":null,"RIVERNAME":"冬山河","BASIN_NO":"2550","BASIN_NAME":"冬山河","AREA":93.39652080393776}},{"type":"MultiLineString","arcs":[[3]],"properties":{"id":null,"RIVERNAME":"冬山河","BASIN_NO":"2550","BASIN_NAME":"冬山河","AREA":93.39652080393776}},{"type":"MultiLineString","arcs":[[4]],"properties":{"id":null,"RIVERNAME":"冬山河","BASIN_NO":"2550","BASIN_NAME":"冬山河","AREA":93.39652080393776}},{"type":"MultiLineString","arcs":[[5]],"properties":{"id":null,"RIVERNAME":"冬山河","BASIN_NO":"2550","BASIN_NAME":"冬山河","AREA":93.39652080393776}},{"type":"MultiLineString","arcs":[[6]],"properties":{"id":null,"RIVERNAME":"冬山河","BASIN_NO":"2550","BASIN_NAME":"冬山河","AREA":93.39652080393776}},{"type":"MultiLineString","arcs":[[7]],"properties":{"id":null,"RIVERNAME":"冬山河","BASIN_NO":"2550","BASIN_NAME":"冬山河","AREA":93.39652080393776}},{"type":"MultiLineString","arcs":[[8]],"properties":{"id":null,"RIVERNAME":"冬山河","BASIN_NO":"2550","BASIN_NAME":"冬山河","AREA":93.39652080393776}},{"type":"MultiLineString","arcs":[[9]],"properties":{"id":null,"RIVERNAME":"冬山河","BASIN_NO":"2550","BASIN_NAME":"冬山河","AREA":93.39652080393776}},{"type":"MultiLineString","arcs":[[10]],"properties":{"id":null,"RIVERNAME":"冬山河","BASIN_NO":"2550","BASIN_NAME":"冬山河","AREA":93.39652080393776}},{"type":"MultiLineString","arcs":[[11]],"properties":{"id":null,"RIVERNAME":"冬山河","BASIN_NO":"2550","BASIN_NAME":"冬山河","AREA":93.39652080393776}},{"type":"MultiLineString","arcs":[[12]],"properties":{"id":null,"RIVERNAME":"冬山河","BASIN_NO":"2550","BASIN_NAME":"冬山河","AREA":93.39652080393776}},{"type":"MultiLineString","arcs":[[13]],"properties":{"id":null,"RIVERNAME":"冬山河","BASIN_NO":"2550","BASIN_NAME":"冬山河","AREA":93.39652080393776}},{"type":"MultiLineString","arcs":[[14]],"properties":{"id":null,"RIVERNAME":"冬山河","BASIN_NO":"2550","BASIN_NAME":"冬山河","AREA":93.39652080393776}},{"type":"MultiLineString","arcs":[[15]],"properties":{"id":null,"RIVERNAME":"冬山河","BASIN_NO":"2550","BASIN_NAME":"冬山河","AREA":93.39652080393776}},{"type":"MultiLineString","arcs":[[16]],"properties":{"id":null,"RIVERNAME":"冬山河","BASIN_NO":"2550","BASIN_NAME":"冬山河","AREA":93.39652080393776}},{"type":"MultiLineString","arcs":[[17]],"properties":{"id":null,"RIVERNAME":null,"BASIN_NO":"2550","BASIN_NAME":"冬山河","AREA":93.39652080393776}},{"type":"MultiLineString","arcs":[[18]],"properties":{"id":null,"RIVERNAME":null,"BASIN_NO":"2550","BASIN_NAME":"冬山河","AREA":93.39652080393776}},{"type":"MultiLineString","arcs":[[19]],"properties":{"id":null,"RIVERNAME":"冬山河","BASIN_NO":"2550","BASIN_NAME":"冬山河","AREA":93.39652080393776}},{"type":"MultiLineString","arcs":[[20]],"properties":{"id":null,"RIVERNAME":null,"BASIN_NO":"2550","BASIN_NAME":"冬山河","AREA":93.39652080393776}},{"type":"MultiLineString","arcs":[[21]],"properties":{"id":null,"RIVERNAME":"冬山河","BASIN_NO":"2550","BASIN_NAME":"冬山河","AREA":93.39652080393776}},{"type":"MultiLineString","arcs":[[22]],"properties":{"id":null,"RIVERNAME":"冬山河","BASIN_NO":"2550","BASIN_NAME":"冬山河","AREA":93.39652080393776}},{"type":"MultiLineString","arcs":[[23]],"properties":{"id":null,"RIVERNAME":null,"BASIN_NO":"2550","BASIN_NAME":"冬山河","AREA":93.39652080393776}},{"type":"MultiLineString","arcs":[[24]],"properties":{"id":null,"RIVERNAME":"冬山河","BASIN_NO":"2550","BASIN_NAME":"冬山河","AREA":93.39652080393776}},{"type":"MultiLineString","arcs":[[25]],"properties":{"id":null,"RIVERNAME":"冬山河","BASIN_NO":"2550","BASIN_NAME":"冬山河","AREA":93.39652080393776}},{"type":"MultiLineString","arcs":[[26]],"properties":{"id":null,"RIVERNAME":null,"BASIN_NO":"2550","BASIN_NAME":"冬山河","AREA":93.39652080393776}},{"type":"MultiLineString","arcs":[[27]],"properties":{"id":null,"RIVERNAME":null,"BASIN_NO":"2550","BASIN_NAME":"冬山河","AREA":93.39652080393776}},{"type":"MultiLineString","arcs":[[28]],"properties":{"id":null,"RIVERNAME":null,"BASIN_NO":"2550","BASIN_NAME":"冬山河","AREA":93.39652080393776}},{"type":"MultiLineString","arcs":[[29]],"properties":{"id":null,"RIVERNAME":"冬山河","BASIN_NO":"2550","BASIN_NAME":"冬山河","AREA":93.39652080393776}},{"type":"MultiLineString","arcs":[[30]],"properties":{"id":null,"RIVERNAME":null,"BASIN_NO":"2550","BASIN_NAME":"冬山河","AREA":93.39652080393776}},{"type":"MultiLineString","arcs":[[31]],"properties":{"id":null,"RIVERNAME":null,"BASIN_NO":"2550","BASIN_NAME":"冬山河","AREA":93.39652080393776}},{"type":"MultiLineString","arcs":[[32]],"properties":{"id":null,"RIVERNAME":"冬山河","BASIN_NO":"2550","BASIN_NAME":"冬山河","AREA":93.39652080393776}},{"type":"MultiLineString","arcs":[[33]],"properties":{"id":null,"RIVERNAME":null,"BASIN_NO":"2550","BASIN_NAME":"冬山河","AREA":93.39652080393776}},{"type":"MultiLineString","arcs":[[34]],"properties":{"id":null,"RIVERNAME":"冬山河","BASIN_NO":"2550","BASIN_NAME":"冬山河","AREA":93.39652080393776}},{"type":"MultiLineString","arcs":[[35]],"properties":{"id":null,"RIVERNAME":null,"BASIN_NO":"2550","BASIN_NAME":"冬山河","AREA":93.39652080393776}},{"type":"MultiLineString","arcs":[[36]],"properties":{"id":null,"RIVERNAME":null,"BASIN_NO":"2550","BASIN_NAME":"冬山河","AREA":93.39652080393776}},{"type":"MultiLineString","arcs":[[37]],"properties":{"id":null,"RIVERNAME":null,"BASIN_NO":"2550","BASIN_NAME":"冬山河","AREA":93.39652080393776}},{"type":"MultiLineString","arcs":[[38]],"properties":{"id":null,"RIVERNAME":null,"BASIN_NO":"2550","BASIN_NAME":"冬山河","AREA":93.39652080393776}},{"type":"MultiLineString","arcs":[[39]],"properties":{"id":null,"RIVERNAME":null,"BASIN_NO":"2550","BASIN_NAME":"冬山河","AREA":93.39652080393776}},{"type":"MultiLineString","arcs":[[40]],"properties":{"id":null,"RIVERNAME":"新寮溪","BASIN_NO":"2550","BASIN_NAME":"冬山河","AREA":93.39652080393776}},{"type":"MultiLineString","arcs":[[41]],"properties":{"id":null,"RIVERNAME":"舊寮溪","BASIN_NO":"2550","BASIN_NAME":"冬山河","AREA":93.39652080393776}},{"type":"MultiLineString","arcs":[[42]],"properties":{"id":null,"RIVERNAME":"新寮溪","BASIN_NO":"2550","BASIN_NAME":"冬山河","AREA":93.39652080393776}},{"type":"MultiLineString","arcs":[[43]],"properties":{"id":null,"RIVERNAME":"冬山河","BASIN_NO":"2550","BASIN_NAME":"冬山河","AREA":93.39652080393776}},{"type":"MultiLineString","arcs":[[44]],"properties":{"id":null,"RIVERNAME":"新寮溪","BASIN_NO":"2550","BASIN_NAME":"冬山河","AREA":93.39652080393776}},{"type":"MultiLineString","arcs":[[45]],"properties":{"id":null,"RIVERNAME":null,"BASIN_NO":"2550","BASIN_NAME":"冬山河","AREA":93.39652080393776}},{"type":"MultiLineString","arcs":[[46]],"properties":{"id":null,"RIVERNAME":"冬山河","BASIN_NO":"2550","BASIN_NAME":"冬山河","AREA":93.39652080393776}},{"type":"MultiLineString","arcs":[[47]],"properties":{"id":null,"RIVERNAME":"舊寮溪","BASIN_NO":"2550","BASIN_NAME":"冬山河","AREA":93.39652080393776}},{"type":"MultiLineString","arcs":[[48]],"properties":{"id":null,"RIVERNAME":"舊寮溪","BASIN_NO":"2550","BASIN_NAME":"冬山河","AREA":93.39652080393776}},{"type":"MultiLineString","arcs":[[49]],"properties":{"id":null,"RIVERNAME":"舊寮溪","BASIN_NO":"2550","BASIN_NAME":"冬山河","AREA":93.39652080393776}},{"type":"MultiLineString","arcs":[[50]],"properties":{"id":null,"RIVERNAME":"安平坑","BASIN_NO":"2550","BASIN_NAME":"冬山河","AREA":93.39652080393776}},{"type":"MultiLineString","arcs":[[51]],"properties":{"id":null,"RIVERNAME":"舊寮溪","BASIN_NO":"2550","BASIN_NAME":"冬山河","AREA":93.39652080393776}},{"type":"MultiLineString","arcs":[[52]],"properties":{"id":null,"RIVERNAME":null,"BASIN_NO":"2550","BASIN_NAME":"冬山河","AREA":93.39652080393776}},{"type":"MultiLineString","arcs":[[53]],"properties":{"id":null,"RIVERNAME":"舊寮溪","BASIN_NO":"2550","BASIN_NAME":"冬山河","AREA":93.39652080393776}},{"type":"MultiLineString","arcs":[[54]],"properties":{"id":null,"RIVERNAME":"舊寮溪","BASIN_NO":"2550","BASIN_NAME":"冬山河","AREA":93.39652080393776}},{"type":"MultiLineString","arcs":[[55]],"properties":{"id":null,"RIVERNAME":"新寮溪","BASIN_NO":"2550","BASIN_NAME":"冬山河","AREA":93.39652080393776}},{"type":"MultiLineString","arcs":[[56]],"properties":{"id":null,"RIVERNAME":null,"BASIN_NO":"2550","BASIN_NAME":"冬山河","AREA":93.39652080393776}},{"type":"MultiLineString","arcs":[[57]],"properties":{"id":null,"RIVERNAME":null,"BASIN_NO":"2550","BASIN_NAME":"冬山河","AREA":93.39652080393776}},{"type":"MultiLineString","arcs":[[58]],"properties":{"id":null,"RIVERNAME":"冬山河","BASIN_NO":"2550","BASIN_NAME":"冬山河","AREA":93.39652080393776}}]}},"arcs":[[[121.829022,24.697386],[121.828617,24.697026]],[[121.828617,24.697026],[121.828617,24.695946],[121.828221,24.695586]],[[121.828221,24.695586],[121.827816,24.695226]],[[121.827816,24.695226],[121.827411,24.694866]],[[121.827411,24.694866],[121.827015,24.694515]],[[121.827015,24.694515],[121.826619,24.694155]],[[121.826619,24.694155],[121.826223,24.693795]],[[121.826223,24.693795],[121.825827,24.693435]],[[121.825827,24.693435],[121.825431,24.693075]],[[121.825431,24.693075],[121.825035,24.692715]],[[121.825035,24.692715],[121.824639,24.692355]],[[121.824639,24.692355],[121.824243,24.691995]],[[121.824243,24.691995],[121.823838,24.691635]],[[121.823838,24.691635],[121.823442,24.691284]],[[121.823442,24.691284],[121.823046,24.690924]],[[121.823046,24.690924],[121.82265,24.690564]],[[121.82265,24.690564],[121.822254,24.690204]],[[121.792599,24.690006],[121.792995,24.689997],[121.7934,24.690357],[121.7934,24.690357],[121.793787,24.689997],[121.794183,24.689997],[121.794579,24.690348],[121.794579,24.690348],[121.794975,24.689988]],[[121.795767,24.690708],[121.796163,24.690348],[121.795767,24.689988]],[[121.822254,24.690204],[121.821858,24.689844]],[[121.795767,24.689988],[121.795362,24.689628],[121.794975,24.689988]],[[121.821858,24.689844],[121.821453,24.689484]],[[121.821453,24.689484],[121.821057,24.689124]],[[121.828221,24.697395],[121.827078,24.697755],[121.827078,24.697755],[121.825926,24.69744],[121.824774,24.697089],[121.823631,24.697539],[121.823631,24.697539],[121.822479,24.697152],[121.821336,24.697656],[121.821336,24.697656],[121.820184,24.697539],[121.819041,24.697728],[121.819041,24.697728],[121.81788,24.69672],[121.816728,24.695595],[121.815567,24.694542],[121.814424,24.694236],[121.813272,24.693912],[121.81212,24.693291],[121.810968,24.69375],[121.810968,24.69375],[121.809825,24.693705],[121.808565,24.694155],[121.808025,24.694929],[121.807557,24.696288],[121.806324,24.696405],[121.806324,24.696405],[121.804704,24.696351],[121.804452,24.694929],[121.804119,24.69357],[121.803525,24.69231],[121.802319,24.691284],[121.801743,24.690015],[121.800762,24.689124],[121.799466,24.689421],[121.798593,24.6906],[121.798881,24.691878],[121.798881,24.691878],[121.797603,24.691599],[121.795767,24.690708]],[[121.821057,24.689124],[121.820652,24.688764]],[[121.820652,24.688764],[121.820256,24.688404]],[[121.820256,24.688404],[121.81986,24.688053]],[[121.819473,24.688413],[121.81986,24.688053]],[[121.819473,24.688413],[121.818312,24.687288],[121.81716,24.686937],[121.816017,24.686739],[121.814856,24.685731],[121.813704,24.684714],[121.812543,24.683661],[121.811391,24.682608],[121.81023,24.681537],[121.809078,24.680475],[121.807926,24.679404],[121.806774,24.678333],[121.805613,24.677271],[121.804461,24.676227],[121.803309,24.675192],[121.802148,24.674184],[121.800915,24.674094],[121.799619,24.674076],[121.798467,24.673734],[121.797315,24.674049],[121.797315,24.674049],[121.796172,24.673806],[121.79502,24.673545],[121.793877,24.672798],[121.792599,24.672393],[121.791312,24.67161],[121.790178,24.671205],[121.789035,24.670998],[121.786551,24.67089]],[[121.81986,24.688053],[121.820652,24.687324],[121.820643,24.686235],[121.821039,24.685875],[121.825386,24.685848],[121.825773,24.685488],[121.825773,24.685128],[121.822992,24.682617],[121.822983,24.681528],[121.823379,24.681168],[121.82337,24.680088],[121.823757,24.679719],[121.823757,24.678639],[121.822956,24.677919],[121.822956,24.677559],[121.82256,24.677199],[121.82256,24.676839],[121.814208,24.669306]],[[121.814208,24.669306],[121.813812,24.668937]],[[121.814208,24.669306],[121.814595,24.668937]],[[121.813812,24.668937],[121.81302,24.668946],[121.81302,24.668946],[121.797711,24.655122]],[[121.814595,24.668937],[121.814991,24.668577],[121.815396,24.668577],[121.815783,24.668208],[121.817358,24.668199],[121.818933,24.66675],[121.821705,24.666732],[121.822092,24.666372],[121.822092,24.666012],[121.822488,24.665643],[121.822479,24.664923],[121.822866,24.664563],[121.822857,24.662394],[121.823253,24.662025],[121.823649,24.662025],[121.824036,24.661665],[121.824036,24.660945],[121.824423,24.660576],[121.824414,24.659496],[121.82481,24.659136],[121.824801,24.657327],[121.825197,24.656967],[121.825179,24.654438],[121.826358,24.653349],[121.826349,24.6519],[121.826736,24.65154],[121.826727,24.650091],[121.826331,24.649731]],[[121.797711,24.655122],[121.797909,24.654582],[121.797117,24.653862],[121.797108,24.653502],[121.796712,24.653142],[121.796712,24.652782],[121.796316,24.652422],[121.796316,24.652062],[121.795911,24.651702],[121.795911,24.651342],[121.795515,24.650982],[121.795515,24.650622],[121.795119,24.650262],[121.79511,24.649902],[121.794714,24.649542],[121.794714,24.649182],[121.794318,24.648822],[121.794318,24.648462],[121.793922,24.648102],[121.793913,24.647742],[121.793121,24.647022],[121.793121,24.646662],[121.792725,24.646302],[121.792716,24.645582],[121.79232,24.645222],[121.79232,24.644862]],[[121.79232,24.644862],[121.791843,24.644745]],[[121.758552,24.641388],[121.758075,24.640929]],[[121.797711,24.655122],[121.796739,24.656031],[121.796739,24.656031],[121.796343,24.655671],[121.795947,24.65604],[121.792392,24.656058],[121.792392,24.656058],[121.791591,24.655338],[121.790025,24.656796],[121.790025,24.657156],[121.790421,24.657507],[121.790421,24.657867],[121.789638,24.658596],[121.789242,24.658596],[121.789242,24.658596],[121.788846,24.658245],[121.78845,24.658605],[121.785291,24.658623],[121.784112,24.659712],[121.784112,24.659712],[121.782528,24.658272],[121.782123,24.658641],[121.782123,24.658641],[121.781727,24.658281],[121.78134,24.658281],[121.78134,24.658281],[121.780935,24.657921],[121.780548,24.657921],[121.780548,24.657921],[121.778955,24.65649],[121.778955,24.65613],[121.779342,24.655761],[121.779342,24.655041],[121.778946,24.654681],[121.778937,24.653961],[121.777353,24.652521],[121.776165,24.65253],[121.776165,24.65253],[121.77576,24.65217],[121.775373,24.65217],[121.775373,24.65217],[121.774977,24.65181],[121.773789,24.651819],[121.773402,24.652179],[121.773402,24.652179],[121.771809,24.650748],[121.771413,24.651108],[121.771413,24.651108],[121.770621,24.650388],[121.770225,24.650397],[121.770225,24.650397],[121.769433,24.649677],[121.769424,24.649317],[121.76784,24.647877],[121.767444,24.648237],[121.765473,24.648255],[121.765473,24.648255],[121.764672,24.647535],[121.764285,24.647535],[121.763889,24.647895],[121.763493,24.647904],[121.763493,24.647904],[121.761504,24.646104],[121.761117,24.646464],[121.761117,24.646464],[121.757931,24.643593],[121.757922,24.641784],[121.757526,24.641433],[121.758075,24.640929]],[[121.758075,24.640929],[121.75776,24.640803]],[[121.791843,24.644745],[121.791915,24.644142],[121.791123,24.643422],[121.791123,24.643062],[121.790727,24.642702],[121.790718,24.642342],[121.790322,24.641982],[121.790313,24.640533],[121.789917,24.640182]],[[121.758399,24.637194],[121.757508,24.637104]],[[121.75776,24.640803],[121.757247,24.640488],[121.756977,24.640605],[121.756347,24.640632],[121.756347,24.640632],[121.755933,24.640353],[121.755438,24.639957],[121.75452,24.639048],[121.754304,24.638679],[121.754241,24.638247],[121.754232,24.637536],[121.754232,24.636879],[121.754106,24.636141],[121.753791,24.635682],[121.753512,24.635376],[121.752846,24.634917],[121.752441,24.634665],[121.752369,24.634377]],[[121.757508,24.637104],[121.757103,24.637095],[121.756311,24.636375],[121.756311,24.636015],[121.755519,24.635304],[121.755123,24.635304],[121.755123,24.635304],[121.754727,24.634944],[121.754727,24.634584],[121.754124,24.634044]],[[121.776966,24.631641],[121.776453,24.632109],[121.775958,24.632505],[121.775472,24.632712],[121.774779,24.632937],[121.774068,24.633306],[121.773708,24.633531],[121.773078,24.633855],[121.772808,24.634233],[121.77261,24.6348],[121.772322,24.635439],[121.77207,24.635727],[121.771251,24.635727],[121.771251,24.635727],[121.770585,24.635619],[121.770162,24.63561],[121.769739,24.635727],[121.769379,24.635988],[121.768875,24.636537],[121.768596,24.636798],[121.768002,24.637266],[121.767516,24.637608],[121.767039,24.637932],[121.766625,24.638292],[121.766292,24.638742],[121.766004,24.639147],[121.765779,24.63948],[121.765572,24.639885],[121.765401,24.640299],[121.765302,24.640623],[121.765293,24.640992],[121.765491,24.641622],[121.765842,24.641838],[121.766256,24.641973],[121.766778,24.642198],[121.766994,24.642513],[121.767021,24.642909],[121.766643,24.643503],[121.766319,24.643764],[121.766022,24.643971],[121.766022,24.643971],[121.765365,24.643953],[121.765014,24.643782],[121.76433,24.644259],[121.763979,24.644385],[121.763979,24.644385],[121.76334,24.644088],[121.762926,24.643602],[121.762647,24.643278],[121.762332,24.643017],[121.761711,24.642639],[121.760973,24.642414],[121.760361,24.642243],[121.759686,24.642],[121.75902,24.641667],[121.758552,24.641388]],[[121.775661,24.631614],[121.775013,24.631749],[121.774293,24.631839],[121.773609,24.631965],[121.772979,24.632154],[121.772313,24.632442],[121.771899,24.632712],[121.771458,24.633],[121.771089,24.633171],[121.770738,24.633315],[121.770333,24.633459],[121.769487,24.633621],[121.7691,24.63381],[121.768776,24.634161],[121.768452,24.634368],[121.768452,24.634368],[121.767858,24.634152],[121.76757,24.633783],[121.767201,24.633441],[121.76685,24.633297],[121.766157,24.63327],[121.765545,24.633657],[121.765266,24.633918],[121.764888,24.634377],[121.764492,24.634935],[121.764222,24.635295],[121.763898,24.635565],[121.763538,24.635781],[121.763079,24.63597],[121.762467,24.636168],[121.762089,24.636267],[121.761729,24.636375],[121.761324,24.636456],[121.761324,24.636456],[121.760856,24.636456],[121.760388,24.636348],[121.759866,24.63633],[121.759497,24.636465],[121.758984,24.636879],[121.758399,24.637194]],[[121.776966,24.631641],[121.776732,24.631326],[121.776246,24.631443],[121.775661,24.631614]],[[121.791843,24.644745],[121.791159,24.644259],[121.790646,24.64389],[121.790277,24.643665],[121.789809,24.64317],[121.789341,24.642639],[121.788945,24.642072],[121.788756,24.641613],[121.788531,24.641046],[121.788396,24.640677],[121.788135,24.640092],[121.787703,24.639597],[121.787235,24.639237],[121.786713,24.638769],[121.78647,24.638454],[121.786065,24.637734],[121.785876,24.636987],[121.78575,24.63642],[121.785624,24.635916],[121.785435,24.63525],[121.785309,24.634881],[121.78503,24.63426],[121.784796,24.633936],[121.784202,24.633486],[121.783851,24.633243],[121.783482,24.632991],[121.783068,24.63273],[121.782699,24.632541],[121.782276,24.632325],[121.78188,24.632118],[121.781439,24.631911],[121.780971,24.631686],[121.780305,24.631371],[121.779675,24.631137],[121.779072,24.631002],[121.778505,24.631065],[121.778118,24.631173],[121.777758,24.631281],[121.777389,24.631389],[121.776966,24.631641]],[[121.752369,24.634377],[121.75155,24.633513],[121.75155,24.633153],[121.750758,24.632433],[121.750758,24.632073],[121.750362,24.631713],[121.750353,24.631353],[121.74876,24.629913]],[[121.74876,24.629913],[121.748364,24.629553]],[[121.740372,24.628032],[121.740939,24.628221],[121.741245,24.628509],[121.741245,24.628509],[121.742046,24.628509],[121.74246,24.6285],[121.742829,24.6285],[121.743225,24.6285],[121.743621,24.62886],[121.743621,24.62886],[121.744413,24.628851],[121.744809,24.629211],[121.744809,24.629211],[121.746789,24.629202],[121.747185,24.629562],[121.747185,24.629562],[121.748364,24.629553]],[[121.789917,24.640182],[121.791096,24.639093],[121.791096,24.638733],[121.790691,24.638373],[121.790691,24.637644],[121.790295,24.637284],[121.790295,24.636924],[121.788306,24.635133],[121.789089,24.634404],[121.788693,24.634044],[121.789485,24.633324],[121.789089,24.632964],[121.78908,24.632595],[121.789476,24.632235],[121.789872,24.632235],[121.790259,24.631866],[121.79025,24.631146],[121.789854,24.630795],[121.789854,24.630426],[121.79025,24.630066],[121.789845,24.629706],[121.790241,24.629346],[121.789845,24.628986],[121.789836,24.626817],[121.790619,24.626088]],[[121.740372,24.628032],[121.739598,24.627906],[121.739247,24.627717],[121.738248,24.627528],[121.737474,24.627204],[121.736628,24.626952],[121.735782,24.626502],[121.735422,24.626124],[121.734927,24.625548]],[[121.775661,24.631614],[121.775661,24.631281],[121.775823,24.630975],[121.775823,24.630669],[121.775535,24.630363],[121.775814,24.629976],[121.776066,24.629589],[121.776237,24.629283],[121.775886,24.629247],[121.775391,24.629364],[121.775058,24.629445],[121.774923,24.629859],[121.774923,24.629859],[121.774698,24.629481],[121.774212,24.629679],[121.774212,24.629679],[121.774059,24.629265],[121.774284,24.629085],[121.774554,24.628905],[121.774266,24.628599],[121.773807,24.628581],[121.773906,24.628212],[121.774401,24.627852],[121.773807,24.627672],[121.773366,24.627987],[121.772799,24.628284],[121.771602,24.629004],[121.770261,24.62931],[121.770261,24.62931],[121.769505,24.629085],[121.768659,24.628941],[121.768245,24.62886],[121.767651,24.628095],[121.766634,24.626871],[121.76604,24.625728],[121.766103,24.623109]],[[121.734927,24.625548],[121.734288,24.625737],[121.733442,24.626061],[121.732956,24.626196],[121.732461,24.626196],[121.73175,24.626205],[121.73175,24.626205],[121.73112,24.625755],[121.730472,24.62544],[121.730058,24.625116],[121.729914,24.624468],[121.730121,24.623955],[121.730121,24.623631],[121.729689,24.623244],[121.729338,24.623181],[121.729122,24.622605]],[[121.734927,24.625548],[121.734927,24.6249],[121.735197,24.624315],[121.735548,24.623991],[121.735548,24.623604],[121.735683,24.62328],[121.735971,24.623091],[121.735971,24.622632],[121.736034,24.621858],[121.736169,24.621606]],[[121.754124,24.634044],[121.754313,24.632415],[121.753521,24.631695],[121.753512,24.630975],[121.753116,24.630615],[121.753107,24.629535],[121.752711,24.629175],[121.752711,24.628815],[121.753107,24.628446],[121.752702,24.628095],[121.752693,24.626286],[121.752297,24.625926],[121.752297,24.625566],[121.752684,24.625206],[121.752684,24.624477],[121.753863,24.623388],[121.753863,24.623028],[121.753467,24.622668],[121.753071,24.622677],[121.753071,24.622677],[121.751874,24.621597],[121.75227,24.621228],[121.750677,24.619797],[121.750281,24.619797],[121.750281,24.619797],[121.749885,24.619437],[121.749885,24.619077],[121.749093,24.618357],[121.749876,24.617628],[121.749867,24.616548],[121.750263,24.616188],[121.750263,24.615459],[121.749867,24.615108],[121.749867,24.614748],[121.75065,24.614019],[121.750245,24.613659],[121.750245,24.613299],[121.749849,24.612939],[121.749831,24.61077],[121.749435,24.61041],[121.748256,24.610419]],[[121.828221,24.697395],[121.828617,24.697755],[121.828617,24.697755],[121.828806,24.697584]],[[121.828806,24.697584],[121.829022,24.697386]],[[121.828806,24.697584],[121.829598,24.698313],[121.829661,24.698952],[121.828797,24.700716],[121.828167,24.701571],[121.827177,24.703119],[121.826016,24.704514],[121.825908,24.705846],[121.826385,24.706755],[121.827555,24.707385],[121.828959,24.707538],[121.829832,24.707646],[121.830597,24.707637],[121.831236,24.707637],[121.831821,24.707628],[121.832469,24.70779],[121.833225,24.707889],[121.83363,24.708159],[121.834278,24.708582],[121.834692,24.708897],[121.83516,24.709266],[121.835682,24.709689],[121.835817,24.710814],[121.8357,24.711507],[121.834944,24.712362],[121.834431,24.713118],[121.834197,24.714018],[121.833576,24.714783]]],"bbox":[121.729122,24.61041,121.835817,24.714783]}
